nodemcu_uploader/__init__.py
nodemcu_uploader/__main__.py
nodemcu_uploader/exceptions.py
nodemcu_uploader/luacode.py
nodemcu_uploader/main.py
nodemcu_uploader/serialutils.py
nodemcu_uploader/term.py
nodemcu_uploader/uploader.py
nodemcu_uploader/utils.py
nodemcu_uploader/validate.py
nodemcu_uploader/version.py
nodemcu_uploader-1.0.0.dist-info/LICENSE
nodemcu_uploader-1.0.0.dist-info/METADATA
nodemcu_uploader-1.0.0.dist-info/WHEEL
nodemcu_uploader-1.0.0.dist-info/entry_points.txt
nodemcu_uploader-1.0.0.dist-info/top_level.txt
nodemcu_uploader-1.0.0.dist-info/RECORD
