Metadata-Version: 2.1
Name: nodemcu-uploader
Version: 1.0.0
Summary: tool for uploading files to the filesystem of an ESP8266 running NodeMCU.
Home-page: https://github.com/kmpm/nodemcu-uploader
Author: kmpm
Author-email: me@kmpm.se
License: MIT
Keywords: esp8266,upload,nodemcu
Platform: UNKNOWN
Classifier: Development Status :: 4 - Beta
Classifier: Intended Audience :: Developers
Classifier: Programming Language :: Python :: 3
Requires-Python: >=3.5
Requires-Dist: pyserial (>=3.4)
